cipherFinder/__init__.py
cipherFinder/de_obfs.py
cipherFinder/deleter.py
cipherFinder/finder.py
cipherFinder/plugins.py
cipherFinder/utils.py
FiveMCipherFinder-2.6.3.dist-info/LICENSE
FiveMCipherFinder-2.6.3.dist-info/METADATA
FiveMCipherFinder-2.6.3.dist-info/WHEEL
FiveMCipherFinder-2.6.3.dist-info/entry_points.txt
FiveMCipherFinder-2.6.3.dist-info/top_level.txt
FiveMCipherFinder-2.6.3.dist-info/RECORD
