Metadata-Version: 2.1
Name: FiveMCipherFinder
Version: 2.6.3
Summary: Finds Cipher in lua scripts.
Home-page: https://github.com/exersalza/FivemCipherFinder
Author: exersalza
License: MIT
Project-URL: Source, https://github.com/exersalza/FivemCipherFinder
Project-URL: Issues, https://github.com/exersalza/FivemCipherFinder/issues
Classifier: Intended Audience :: Developers
Classifier: License :: OSI Approved :: MIT License
Classifier: Operating System :: OS Independent
Classifier: Programming Language :: Python :: 3
Classifier: Topic :: Software Development
License-File: LICENSE
Requires-Dist: requests
Requires-Dist: chardet
